{"name":"That '70s Show","imdbId":"tt0165598","lastRefreshed":"2026-07-20","avgRating":7.5,"imdbSeriesRating":8.1,"totalEpisodes":200,"totalSeasons":8,"totalVotes":195194,"episodes":[{"season":1,"episode":1,"title":"That '70s Pilot","rating":7.9,"votes":2193},{"season":1,"episode":2,"title":"Eric's Birthday","rating":8.0,"votes":1762},{"season":1,"episode":3,"title":"Streaking","rating":7.7,"votes":1638},{"season":1,"episode":4,"title":"Battle of the Sexists","rating":7.6,"votes":1544},{"season":1,"episode":5,"title":"Eric's Burger Job","rating":7.6,"votes":1530},{"season":1,"episode":6,"title":"The Keg","rating":8.2,"votes":1594},{"season":1,"episode":7,"title":"That Disco Episode","rating":8.0,"votes":1547},{"season":1,"episode":8,"title":"Drive in","rating":7.7,"votes":1457},{"season":1,"episode":9,"title":"Thanksgiving","rating":7.8,"votes":1452},{"season":1,"episode":10,"title":"Sunday, Bloody Sunday","rating":7.5,"votes":1386},{"season":1,"episode":11,"title":"Eric's Buddy","rating":8.1,"votes":1609},{"season":1,"episode":12,"title":"The Best Christmas Ever","rating":7.9,"votes":1415},{"season":1,"episode":13,"title":"Ski Trip","rating":7.7,"votes":1361},{"season":1,"episode":14,"title":"Stolen Car","rating":7.7,"votes":1324},{"season":1,"episode":15,"title":"That Wrestling Show","rating":7.9,"votes":1459},{"season":1,"episode":16,"title":"First Date","rating":7.7,"votes":1324},{"season":1,"episode":17,"title":"The Pill","rating":8.2,"votes":1373},{"season":1,"episode":18,"title":"The Career Day","rating":7.9,"votes":1359},{"season":1,"episode":19,"title":"Prom Night","rating":7.8,"votes":1358},{"season":1,"episode":20,"title":"A New Hope","rating":8.4,"votes":1501},{"season":1,"episode":21,"title":"Water Tower","rating":8.2,"votes":1364},{"season":1,"episode":22,"title":"Punk Chick","rating":7.4,"votes":1315},{"season":1,"episode":23,"title":"Grandma's Dead","rating":8.1,"votes":1332},{"season":1,"episode":24,"title":"Hyde Moves In","rating":8.1,"votes":1388},{"season":1,"episode":25,"title":"The Good Son","rating":8.0,"votes":1331},{"season":2,"episode":1,"title":"Garage Sale","rating":8.5,"votes":1427},{"season":2,"episode":2,"title":"Red's Last Day","rating":7.7,"votes":1201},{"season":2,"episode":3,"title":"The Velvet Rope","rating":7.5,"votes":1191},{"season":2,"episode":4,"title":"Laurie and the Professor","rating":7.6,"votes":1179},{"season":2,"episode":5,"title":"Halloween","rating":8.1,"votes":1291},{"season":2,"episode":6,"title":"Vanstock","rating":7.8,"votes":1164},{"season":2,"episode":7,"title":"I Love Cake","rating":7.7,"votes":1154},{"season":2,"episode":8,"title":"Sleepover","rating":8.1,"votes":1162},{"season":2,"episode":9,"title":"Eric Gets Suspended","rating":7.7,"votes":1151},{"season":2,"episode":10,"title":"Red's Birthday","rating":7.6,"votes":1117},{"season":2,"episode":11,"title":"Laurie Moves Out","rating":7.6,"votes":1097},{"season":2,"episode":12,"title":"Eric's Stash","rating":7.5,"votes":1104},{"season":2,"episode":13,"title":"Hunting","rating":7.8,"votes":1136},{"season":2,"episode":14,"title":"Red's New Job","rating":7.7,"votes":1083},{"season":2,"episode":15,"title":"Burning Down the House","rating":7.8,"votes":1156},{"season":2,"episode":16,"title":"The First Time","rating":7.9,"votes":1137},{"season":2,"episode":17,"title":"After Glow","rating":7.8,"votes":1098},{"season":2,"episode":18,"title":"Kitty and Eric's Night Out","rating":7.8,"votes":1096},{"season":2,"episode":19,"title":"Parents Find Out","rating":8.2,"votes":1112},{"season":2,"episode":20,"title":"Kiss of Death","rating":7.7,"votes":1063},{"season":2,"episode":21,"title":"Kelso's Serenade","rating":7.5,"votes":1054},{"season":2,"episode":22,"title":"Jackie Moves On","rating":7.3,"votes":1048},{"season":2,"episode":23,"title":"Holy Crap!","rating":7.5,"votes":1086},{"season":2,"episode":24,"title":"Red Fired Up","rating":7.8,"votes":1043},{"season":2,"episode":25,"title":"Cat Fight Club","rating":8.1,"votes":1081},{"season":2,"episode":26,"title":"Moon Over Point Place","rating":7.9,"votes":1079},{"season":3,"episode":1,"title":"Reefer Madness","rating":8.3,"votes":1197},{"season":3,"episode":2,"title":"Red Sees Red","rating":8.2,"votes":1131},{"season":3,"episode":3,"title":"Hyde's Father","rating":7.5,"votes":1046},{"season":3,"episode":4,"title":"Too Old to Trick or Treat, Too Young to Die","rating":8.1,"votes":1339},{"season":3,"episode":5,"title":"Roller Disco","rating":7.6,"votes":1022},{"season":3,"episode":6,"title":"Eric's Panties","rating":8.6,"votes":1317},{"season":3,"episode":7,"title":"Baby Fever","rating":7.3,"votes":992},{"season":3,"episode":8,"title":"Jackie Bags Hyde","rating":8.0,"votes":1050},{"season":3,"episode":9,"title":"Hyde's Christmas Rager","rating":7.6,"votes":1008},{"season":3,"episode":10,"title":"Ice Shack","rating":7.8,"votes":1006},{"season":3,"episode":11,"title":"Who Wants It More?","rating":7.7,"votes":975},{"season":3,"episode":12,"title":"Fez Gets the Girl","rating":7.6,"votes":987},{"season":3,"episode":13,"title":"Dine & Dash","rating":8.7,"votes":1303},{"season":3,"episode":14,"title":"Radio Daze","rating":7.6,"votes":974},{"season":3,"episode":15,"title":"Donna's Panties","rating":7.6,"votes":981},{"season":3,"episode":16,"title":"Romantic Weekend","rating":7.7,"votes":956},{"season":3,"episode":17,"title":"Kitty's Birthday (That's Today?!)","rating":8.0,"votes":1028},{"season":3,"episode":18,"title":"The Trials of M. Kelso","rating":7.7,"votes":966},{"season":3,"episode":19,"title":"Eric's Naughty No-no","rating":7.4,"votes":960},{"season":3,"episode":20,"title":"Holy Craps","rating":7.5,"votes":964},{"season":3,"episode":21,"title":"Fez Dates Donna","rating":7.5,"votes":948},{"season":3,"episode":22,"title":"Eric's Drunken Tattoo","rating":7.6,"votes":976},{"season":3,"episode":23,"title":"Canadian Road Trip","rating":8.2,"votes":1144},{"season":3,"episode":24,"title":"Backstage Pass","rating":7.4,"votes":990},{"season":3,"episode":25,"title":"The Promise Ring","rating":7.7,"votes":976},{"season":4,"episode":1,"title":"It's a Wonderful Life","rating":8.0,"votes":1148},{"season":4,"episode":2,"title":"Eric's Depression","rating":7.6,"votes":965},{"season":4,"episode":3,"title":"Pinciotti vs. Forman","rating":7.5,"votes":924},{"season":4,"episode":4,"title":"Hyde Gets the Girl","rating":7.6,"votes":990},{"season":4,"episode":5,"title":"Bye Bye Basement","rating":7.6,"votes":942},{"season":4,"episode":6,"title":"The Relapse","rating":7.6,"votes":915},{"season":4,"episode":7,"title":"Uncomfortable Ball Stuff","rating":7.4,"votes":909},{"season":4,"episode":8,"title":"Donna's Story","rating":7.3,"votes":913},{"season":4,"episode":9,"title":"The Forgotten Son","rating":7.6,"votes":880},{"season":4,"episode":10,"title":"Red and Stacey","rating":7.8,"votes":964},{"season":4,"episode":11,"title":"The Third Wheel","rating":7.3,"votes":902},{"season":4,"episode":12,"title":"An Eric Forman Christmas","rating":7.4,"votes":956},{"season":4,"episode":13,"title":"Jackie Says Cheese","rating":7.5,"votes":895},{"season":4,"episode":14,"title":"Eric's Hot Cousin","rating":8.2,"votes":1075},{"season":4,"episode":15,"title":"Tornado Prom","rating":7.7,"votes":925},{"season":4,"episode":16,"title":"Donna Dates a Kelso","rating":7.3,"votes":889},{"season":4,"episode":17,"title":"Kelso's Career","rating":7.5,"votes":871},{"season":4,"episode":18,"title":"Leo Loves Kitty","rating":7.3,"votes":864},{"season":4,"episode":19,"title":"Jackie's Cheese Squeeze","rating":7.6,"votes":882},{"season":4,"episode":20,"title":"Class Picture","rating":8.3,"votes":1043},{"season":4,"episode":21,"title":"Prank Day","rating":8.1,"votes":913},{"season":4,"episode":22,"title":"Eric's Corvette Caper","rating":7.7,"votes":882},{"season":4,"episode":23,"title":"Hyde's Birthday","rating":8.1,"votes":911},{"season":4,"episode":24,"title":"That '70s Musical","rating":7.1,"votes":1417},{"season":4,"episode":25,"title":"Eric's False Alarm","rating":7.4,"votes":848},{"season":4,"episode":26,"title":"Everybody Loves Casey","rating":7.6,"votes":863},{"season":4,"episode":27,"title":"Love, Wisconsin Style","rating":8.1,"votes":916},{"season":5,"episode":1,"title":"Going to California","rating":7.8,"votes":934},{"season":5,"episode":2,"title":"I Can't Quit You Babe","rating":7.6,"votes":877},{"season":5,"episode":3,"title":"What Is and What Should Never Be","rating":7.7,"votes":848},{"season":5,"episode":4,"title":"Heartbreaker","rating":7.6,"votes":858},{"season":5,"episode":5,"title":"Ramble On","rating":7.4,"votes":844},{"season":5,"episode":6,"title":"Over the Hills and Far Away","rating":7.6,"votes":863},{"season":5,"episode":7,"title":"Hot Dog","rating":7.6,"votes":828},{"season":5,"episode":8,"title":"Thank You","rating":7.8,"votes":834},{"season":5,"episode":9,"title":"Black Dog","rating":7.6,"votes":837},{"season":5,"episode":10,"title":"The Crunge","rating":7.6,"votes":814},{"season":5,"episode":11,"title":"The Girl I Love","rating":7.3,"votes":817},{"season":5,"episode":12,"title":"Misty Mountain Hop","rating":8.0,"votes":896},{"season":5,"episode":13,"title":"Your Time Is Gonna Come","rating":7.6,"votes":838},{"season":5,"episode":14,"title":"Babe I'm Gonna Leave You","rating":7.5,"votes":832},{"season":5,"episode":15,"title":"When the Levee Breaks","rating":7.6,"votes":810},{"season":5,"episode":16,"title":"Whole Lotta Love","rating":7.5,"votes":808},{"season":5,"episode":17,"title":"The Battle of Evermore","rating":7.5,"votes":824},{"season":5,"episode":18,"title":"Hey Hey What Can I Do","rating":7.6,"votes":813},{"season":5,"episode":19,"title":"Bring It on Home","rating":7.4,"votes":809},{"season":5,"episode":20,"title":"No Quarter","rating":7.4,"votes":790},{"season":5,"episode":21,"title":"Trampled Under Foot","rating":7.3,"votes":791},{"season":5,"episode":22,"title":"You Shook Me","rating":8.0,"votes":835},{"season":5,"episode":23,"title":"Nobody's Fault But Mine","rating":7.6,"votes":797},{"season":5,"episode":24,"title":"Immigrant Song","rating":7.9,"votes":824},{"season":5,"episode":25,"title":"Celebration Day","rating":8.3,"votes":883},{"season":6,"episode":1,"title":"The Kids Are Alright","rating":7.6,"votes":859},{"season":6,"episode":2,"title":"Join Together","rating":7.4,"votes":793},{"season":6,"episode":3,"title":"Magic Bus","rating":7.7,"votes":806},{"season":6,"episode":4,"title":"The Acid Queen","rating":7.6,"votes":811},{"season":6,"episode":5,"title":"I'm Free","rating":7.4,"votes":788},{"season":6,"episode":6,"title":"We're Not Gonna Take It","rating":7.5,"votes":779},{"season":6,"episode":7,"title":"Christmas","rating":7.6,"votes":824},{"season":6,"episode":8,"title":"I'm a Boy","rating":7.3,"votes":784},{"season":6,"episode":9,"title":"Young Man Blues","rating":7.7,"votes":800},{"season":6,"episode":10,"title":"A Legal Matter","rating":7.5,"votes":773},{"season":6,"episode":11,"title":"I Can See for Miles","rating":7.3,"votes":770},{"season":6,"episode":12,"title":"Sally Simpson","rating":7.3,"votes":801},{"season":6,"episode":13,"title":"Won't Get Fooled Again","rating":7.3,"votes":775},{"season":6,"episode":14,"title":"Baby Don't You Do It","rating":7.5,"votes":794},{"season":6,"episode":15,"title":"Who Are You","rating":7.2,"votes":770},{"season":6,"episode":16,"title":"Man with Money","rating":7.6,"votes":767},{"season":6,"episode":17,"title":"Happy Jack","rating":7.6,"votes":780},{"season":6,"episode":18,"title":"Do You Think It's Alright?","rating":7.3,"votes":745},{"season":6,"episode":19,"title":"Substitute","rating":7.2,"votes":743},{"season":6,"episode":20,"title":"Squeeze Box","rating":7.6,"votes":784},{"season":6,"episode":21,"title":"5:15","rating":7.3,"votes":769},{"season":6,"episode":22,"title":"Sparks","rating":8.0,"votes":798},{"season":6,"episode":23,"title":"My Wife","rating":7.3,"votes":749},{"season":6,"episode":24,"title":"Going Mobile","rating":7.3,"votes":751},{"season":6,"episode":25,"title":"The Seeker","rating":7.5,"votes":751},{"season":7,"episode":1,"title":"Time Is on My Side","rating":7.3,"votes":760},{"season":7,"episode":2,"title":"Let's Spend the Night Together","rating":7.3,"votes":753},{"season":7,"episode":3,"title":"(I Can't Get No) Satisfaction","rating":7.2,"votes":741},{"season":7,"episode":4,"title":"Beast of Burden","rating":7.3,"votes":732},{"season":7,"episode":5,"title":"It's Only Rock and Roll","rating":7.1,"votes":725},{"season":7,"episode":6,"title":"Rip This Joint","rating":7.1,"votes":735},{"season":7,"episode":7,"title":"Mother's Little Helper","rating":7.4,"votes":835},{"season":7,"episode":8,"title":"Angie","rating":7.2,"votes":772},{"season":7,"episode":9,"title":"You Can't Always Get What You Want","rating":7.2,"votes":749},{"season":7,"episode":10,"title":"Surprise, Surprise","rating":7.4,"votes":749},{"season":7,"episode":11,"title":"Winter","rating":7.4,"votes":739},{"season":7,"episode":12,"title":"Don't Lie to Me","rating":7.2,"votes":780},{"season":7,"episode":13,"title":"Can't You Hear Me Knocking","rating":7.9,"votes":835},{"season":7,"episode":14,"title":"Street Fighting Man","rating":7.9,"votes":779},{"season":7,"episode":15,"title":"It's All Over Now","rating":7.3,"votes":768},{"season":7,"episode":16,"title":"On with the Show","rating":7.1,"votes":730},{"season":7,"episode":17,"title":"Down the Road Apiece","rating":7.2,"votes":731},{"season":7,"episode":18,"title":"Oh, Baby We Got a Good Thing Goin'","rating":7.1,"votes":725},{"season":7,"episode":19,"title":"Who's Been Sleeping Here?","rating":7.1,"votes":707},{"season":7,"episode":20,"title":"Gimme Shelter","rating":7.2,"votes":711},{"season":7,"episode":21,"title":"2120 So. Michigan Ave","rating":7.3,"votes":736},{"season":7,"episode":22,"title":"2000 Light Years from Home","rating":7.1,"votes":727},{"season":7,"episode":23,"title":"Take It or Leave It","rating":7.2,"votes":728},{"season":7,"episode":24,"title":"Short and Curlies","rating":7.5,"votes":751},{"season":7,"episode":25,"title":"Till the Next Goodbye","rating":8.1,"votes":859},{"season":8,"episode":1,"title":"Bohemian Rhapsody","rating":7.2,"votes":854},{"season":8,"episode":2,"title":"Somebody to Love","rating":6.7,"votes":791},{"season":8,"episode":3,"title":"You're My Best Friend","rating":6.4,"votes":776},{"season":8,"episode":4,"title":"Misfire","rating":7.0,"votes":810},{"season":8,"episode":5,"title":"Stone Cold Crazy","rating":7.0,"votes":777},{"season":8,"episode":6,"title":"Long Away","rating":6.5,"votes":737},{"season":8,"episode":7,"title":"Fun It","rating":6.7,"votes":776},{"season":8,"episode":8,"title":"Good Company","rating":6.5,"votes":728},{"season":8,"episode":9,"title":"Who Needs You","rating":6.4,"votes":730},{"season":8,"episode":10,"title":"Sweet Lady","rating":6.2,"votes":747},{"season":8,"episode":11,"title":"Good Old Fashioned Lover Boy","rating":6.3,"votes":715},{"season":8,"episode":12,"title":"Killer Queen","rating":6.4,"votes":719},{"season":8,"episode":13,"title":"Spread Your Wings","rating":6.3,"votes":723},{"season":8,"episode":14,"title":"Son and Daughter","rating":6.4,"votes":704},{"season":8,"episode":15,"title":"Keep Yourself Alive","rating":6.3,"votes":709},{"season":8,"episode":16,"title":"My Fairy King","rating":6.5,"votes":716},{"season":8,"episode":17,"title":"Crazy Little Thing Called Love","rating":6.4,"votes":708},{"season":8,"episode":18,"title":"We Will Rock You","rating":6.5,"votes":758},{"season":8,"episode":19,"title":"Sheer Heart Attack","rating":6.4,"votes":722},{"season":8,"episode":20,"title":"Leaving Home Ain't Easy","rating":6.5,"votes":709},{"season":8,"episode":21,"title":"Love of My Life","rating":7.3,"votes":828},{"season":8,"episode":22,"title":"That '70s Finale","rating":8.9,"votes":1868}]}